assets/__init__.py
assets/balaitous.npz
balaitous/__init__.py
balaitous/balaitous.py
balaitous/cli.py
balaitous/transforms.py
balaitous/vit.py
balaitous-1.2.dist-info/LICENSE
balaitous-1.2.dist-info/METADATA
balaitous-1.2.dist-info/WHEEL
balaitous-1.2.dist-info/entry_points.txt
balaitous-1.2.dist-info/top_level.txt
balaitous-1.2.dist-info/RECORD
