Metadata-Version: 2.1
Name: balaitous
Version: 1.2
Summary: Codebase to run the Balaitous model
Author: Simon Jégou
License: MIT
License-File: LICENSE
Requires-Dist: numpy
Requires-Dist: SimpleITK
Requires-Dist: scikit-image
Requires-Dist: torch
Requires-Dist: torchvision
Requires-Dist: lungmask
